pyicumessageformat/__init__.py
pyicumessageformat/constants.py
pyicumessageformat/parser.py
pyicumessageformat-1.0.0.dist-info/LICENSE
pyicumessageformat-1.0.0.dist-info/METADATA
pyicumessageformat-1.0.0.dist-info/WHEEL
pyicumessageformat-1.0.0.dist-info/top_level.txt
pyicumessageformat-1.0.0.dist-info/RECORD
