Metadata-Version: 2.1
Name: pyicumessageformat
Version: 1.0.0
Summary: An unopinionated parser for ICU MessageFormat.
Home-page: https://github.com/sirstendec/pyicumessageformat
Author: Mike
Author-email: sir@stendec.me
License: UNKNOWN
Project-URL: Bug Tracker, https://github.com/sirstendec/pyicumessageformat/issues
Platform: UNKNOWN
Classifier: Programming Language :: Python :: 3
Classifier: License :: OSI Approved :: MIT License
Classifier: Operating System :: OS Independent
Requires-Python: >=3.6
License-File: LICENSE
